sigma/pipelines/rclinuxedr/__init__.py
sigma/pipelines/rclinuxedr/rclinuxedr.py
pysigma_pipeline_rclinuxedr-0.1.0.dist-info/LICENSE
pysigma_pipeline_rclinuxedr-0.1.0.dist-info/METADATA
pysigma_pipeline_rclinuxedr-0.1.0.dist-info/WHEEL
pysigma_pipeline_rclinuxedr-0.1.0.dist-info/RECORD
