Metadata-Version: 2.1
Name: pySigma-pipeline-rclinuxedr
Version: 0.1.0
Summary: pySigma RC LinuxEDR pipeline
Home-page: https://github.com/7RedViolin/pySigma-pipeline-rclinuxedr
License: MIT
Author: Cori Smith
Author-email: cs2718281@gmail.com
Requires-Python: >=3.8,<4.0
Classifier: License :: OSI Approved :: MIT License
Classifier: Programming Language :: Python :: 3
Classifier: Programming Language :: Python :: 3.8
Classifier: Programming Language :: Python :: 3.9
Classifier: Programming Language :: Python :: 3.10
Classifier: Programming Language :: Python :: 3.11
Classifier: Programming Language :: Python :: 3.12
Requires-Dist: pysigma (>=0.11.4,<0.12.0)
Project-URL: Repository, https://github.com/7RedViolin/pySigma-pipeline-rclinuxedr
